kerfed/protos/__init__.py
kerfed/protos/api/v1/__init__.py
kerfed/protos/api/v1/geometry_pb2.py
kerfed/protos/api/v1/geometry_pb2.pyi
kerfed/protos/api/v1/geometry_pb2_grpc.py
kerfed/protos/api/v1/py.typed
kerfed/protos/common/v1/__init__.py
kerfed/protos/common/v1/address_pb2.py
kerfed/protos/common/v1/address_pb2.pyi
kerfed/protos/common/v1/address_pb2_grpc.py
kerfed/protos/common/v1/brand_pb2.py
kerfed/protos/common/v1/brand_pb2.pyi
kerfed/protos/common/v1/brand_pb2_grpc.py
kerfed/protos/common/v1/config_pb2.py
kerfed/protos/common/v1/config_pb2.pyi
kerfed/protos/common/v1/config_pb2_grpc.py
kerfed/protos/common/v1/cots_pb2.py
kerfed/protos/common/v1/cots_pb2.pyi
kerfed/protos/common/v1/cots_pb2_grpc.py
kerfed/protos/common/v1/discount_pb2.py
kerfed/protos/common/v1/discount_pb2.pyi
kerfed/protos/common/v1/discount_pb2_grpc.py
kerfed/protos/common/v1/error_pb2.py
kerfed/protos/common/v1/error_pb2.pyi
kerfed/protos/common/v1/error_pb2_grpc.py
kerfed/protos/common/v1/fab_pb2.py
kerfed/protos/common/v1/fab_pb2.pyi
kerfed/protos/common/v1/fab_pb2_grpc.py
kerfed/protos/common/v1/fileblob_pb2.py
kerfed/protos/common/v1/fileblob_pb2.pyi
kerfed/protos/common/v1/fileblob_pb2_grpc.py
kerfed/protos/common/v1/geometry_pb2.py
kerfed/protos/common/v1/geometry_pb2.pyi
kerfed/protos/common/v1/geometry_pb2_grpc.py
kerfed/protos/common/v1/machine_pb2.py
kerfed/protos/common/v1/machine_pb2.pyi
kerfed/protos/common/v1/machine_pb2_grpc.py
kerfed/protos/common/v1/mill_pb2.py
kerfed/protos/common/v1/mill_pb2.pyi
kerfed/protos/common/v1/mill_pb2_grpc.py
kerfed/protos/common/v1/model_pb2.py
kerfed/protos/common/v1/model_pb2.pyi
kerfed/protos/common/v1/model_pb2_grpc.py
kerfed/protos/common/v1/money_pb2.py
kerfed/protos/common/v1/money_pb2.pyi
kerfed/protos/common/v1/money_pb2_grpc.py
kerfed/protos/common/v1/ndarray_pb2.py
kerfed/protos/common/v1/ndarray_pb2.pyi
kerfed/protos/common/v1/ndarray_pb2_grpc.py
kerfed/protos/common/v1/operation_pb2.py
kerfed/protos/common/v1/operation_pb2.pyi
kerfed_protos-0.2.62.dist-info/METADATA
kerfed_protos-0.2.62.dist-info/WHEEL
kerfed_protos-0.2.62.dist-info/top_level.txt
kerfed_protos-0.2.62.dist-info/RECORD
