Metadata-Version: 2.4
Name: kerfed.protos
Version: 0.2.62
Summary: Built Python bindings for the Kerfed Proto messages.
License: proprietary
Requires-Python: >=3.8
Requires-Dist: protobuf
Requires-Dist: grpcio
Provides-Extra: typed
Requires-Dist: mypy; extra == "typed"
Requires-Dist: grpc-stubs; extra == "typed"
Requires-Dist: types-protobuf; extra == "typed"
Provides-Extra: tests
Requires-Dist: pytest; extra == "tests"
Requires-Dist: trimesh; extra == "tests"
